sigmaa_crawler/__init__.py
sigmaa_crawler/models/__init__.py
sigmaa_crawler/models/user.py
sigmaa_crawler/utils/__init__.py
sigmaa_crawler/utils/session.py
sigmaa_crawler-0.0.2.dist-info/LICENSE
sigmaa_crawler-0.0.2.dist-info/METADATA
sigmaa_crawler-0.0.2.dist-info/WHEEL
sigmaa_crawler-0.0.2.dist-info/top_level.txt
sigmaa_crawler-0.0.2.dist-info/RECORD
