Metadata-Version: 2.1
Name: sigmaa-crawler
Version: 0.0.2
Summary: Este proyecto permite obtener datos del SIGMAA, el sistema educativo de la Universidad del Caribe. Facilita la obtención de información del estudiante, calificaciones, cárdex, oferta académica, información de pagos de estudiantes, entre otros datos, a través de un SDK de Python.
Home-page: https://github.com/unicaribe-dev/sigmaa-crawler
Author: Kenneth Díaz
Author-email: admin@unicaribe.dev
License: MIT
Classifier: Programming Language :: Python :: 3.12
Classifier: License :: OSI Approved :: MIT License
Classifier: Operating System :: OS Independent
License-File: LICENSE
Requires-Dist: requests
Requires-Dist: beautifulsoup4
